package_helper_3_test_01/__init__.py
package_helper_3_test_01/package_helper_3_test_01.py
package_helper_3_test_01/sub_package_1/__init__.py
package_helper_3_test_01/sub_package_1/my_class_1.py
package_helper_3_test_01/sub_package_2/__init__.py
package_helper_3_test_01/sub_package_2/my_class_2.py
package_helper_3_test_01/sub_package_2/my_class_3.py
package_helper_3_test_01-0.1.1.dist-info/LICENSE
package_helper_3_test_01-0.1.1.dist-info/METADATA
package_helper_3_test_01-0.1.1.dist-info/WHEEL
package_helper_3_test_01-0.1.1.dist-info/RECORD
