Metadata-Version: 2.1
Name: package-helper-3-test-01
Version: 0.1.1
Summary: This is a test of Package Helper 3.
Home-page: https://github.com/francois-durand/package-helper-3-test-01
Author: François Durand
Author-email: fradurand@gmail.com
Requires-Python: >=3.9,<4.0
Classifier: Programming Language :: Python :: 3
Classifier: Programming Language :: Python :: 3.9
Classifier: Programming Language :: Python :: 3.10
Classifier: Programming Language :: Python :: 3.11
Project-URL: Documentation, https://francois-durand.github.io/package-helper-3-test-01
Project-URL: Repository, https://github.com/francois-durand/package-helper-3-test-01
